{"type": "CGSHOP2023_Solution",
"instance": "socg92",
"polygons": [
[{"x": {"num": 448,"den": 1}, "y": {"num": 144,"den": 1}}, {"x": {"num": 493,"den": 1}, "y": {"num": 144,"den": 1}}, {"x": {"num": 493,"den": 1}, "y": {"num": 288,"den": 1}}, {"x": {"num": 448,"den": 1}, "y": {"num": 288,"den": 1}}],
[{"x": {"num": 448,"den": 1}, "y": {"num": 256,"den": 1}}, {"x": {"num": 493,"den": 1}, "y": {"num": 224,"den": 1}}, {"x": {"num": 538,"den": 1}, "y": {"num": 224,"den": 1}}, {"x": {"num": 448,"den": 1}, "y": {"num": 288,"den": 1}}],
[{"x": {"num": 112,"den": 1}, "y": {"num": 176,"den": 1}}, {"x": {"num": 538,"den": 1}, "y": {"num": 176,"den": 1}}, {"x": {"num": 493,"den": 1}, "y": {"num": 208,"den": 1}}, {"x": {"num": 410,"den": 1}, "y": {"num": 256,"den": 1}}, {"x": {"num": 157,"den": 1}, "y": {"num": 256,"den": 1}}, {"x": {"num": 112,"den": 1}, "y": {"num": 224,"den": 1}}],
[{"x": {"num": 112,"den": 1}, "y": {"num": 144,"den": 1}}, {"x": {"num": 157,"den": 1}, "y": {"num": 144,"den": 1}}, {"x": {"num": 157,"den": 1}, "y": {"num": 288,"den": 1}}, {"x": {"num": 112,"den": 1}, "y": {"num": 288,"den": 1}}],
[{"x": {"num": 64,"den": 1}, "y": {"num": 176,"den": 1}}, {"x": {"num": 538,"den": 1}, "y": {"num": 176,"den": 1}}, {"x": {"num": 538,"den": 1}, "y": {"num": 208,"den": 1}}, {"x": {"num": 64,"den": 1}, "y": {"num": 208,"den": 1}}],
[{"x": {"num": 314,"den": 1}, "y": {"num": 288,"den": 1}}, {"x": {"num": 442,"den": 1}, "y": {"num": 288,"den": 1}}, {"x": {"num": 442,"den": 1}, "y": {"num": 320,"den": 1}}, {"x": {"num": 314,"den": 1}, "y": {"num": 320,"den": 1}}],
[{"x": {"num": 330,"den": 1}, "y": {"num": 112,"den": 1}}, {"x": {"num": 410,"den": 1}, "y": {"num": 112,"den": 1}}, {"x": {"num": 410,"den": 1}, "y": {"num": 320,"den": 1}}, {"x": {"num": 378,"den": 1}, "y": {"num": 320,"den": 1}}, {"x": {"num": 330,"den": 1}, "y": {"num": 288,"den": 1}}],
[{"x": {"num": 160,"den": 1}, "y": {"num": 320,"den": 1}}, {"x": {"num": 192,"den": 1}, "y": {"num": 288,"den": 1}}, {"x": {"num": 410,"den": 1}, "y": {"num": 112,"den": 1}}, {"x": {"num": 442,"den": 1}, "y": {"num": 112,"den": 1}}, {"x": {"num": 410,"den": 1}, "y": {"num": 144,"den": 1}}, {"x": {"num": 192,"den": 1}, "y": {"num": 320,"den": 1}}],
[{"x": {"num": 378,"den": 1}, "y": {"num": 64,"den": 1}}, {"x": {"num": 410,"den": 1}, "y": {"num": 64,"den": 1}}, {"x": {"num": 410,"den": 1}, "y": {"num": 384,"den": 1}}, {"x": {"num": 378,"den": 1}, "y": {"num": 384,"den": 1}}],
[{"x": {"num": 192,"den": 1}, "y": {"num": 64,"den": 1}}, {"x": {"num": 224,"den": 1}, "y": {"num": 64,"den": 1}}, {"x": {"num": 224,"den": 1}, "y": {"num": 384,"den": 1}}, {"x": {"num": 192,"den": 1}, "y": {"num": 384,"den": 1}}],
[{"x": {"num": 112,"den": 1}, "y": {"num": 224,"den": 1}}, {"x": {"num": 157,"den": 1}, "y": {"num": 176,"den": 1}}, {"x": {"num": 448,"den": 1}, "y": {"num": 176,"den": 1}}, {"x": {"num": 448,"den": 1}, "y": {"num": 256,"den": 1}}, {"x": {"num": 157,"den": 1}, "y": {"num": 256,"den": 1}}],
[{"x": {"num": 112,"den": 1}, "y": {"num": 256,"den": 1}}, {"x": {"num": 272,"den": 1}, "y": {"num": 112,"den": 1}}, {"x": {"num": 304,"den": 1}, "y": {"num": 112,"den": 1}}, {"x": {"num": 272,"den": 1}, "y": {"num": 144,"den": 1}}, {"x": {"num": 157,"den": 1}, "y": {"num": 256,"den": 1}}, {"x": {"num": 112,"den": 1}, "y": {"num": 288,"den": 1}}],
[{"x": {"num": 192,"den": 1}, "y": {"num": 112,"den": 1}}, {"x": {"num": 272,"den": 1}, "y": {"num": 112,"den": 1}}, {"x": {"num": 272,"den": 1}, "y": {"num": 320,"den": 1}}, {"x": {"num": 240,"den": 1}, "y": {"num": 320,"den": 1}}, {"x": {"num": 192,"den": 1}, "y": {"num": 288,"den": 1}}],
[{"x": {"num": 330,"den": 1}, "y": {"num": 64,"den": 1}}, {"x": {"num": 362,"den": 1}, "y": {"num": 64,"den": 1}}, {"x": {"num": 362,"den": 1}, "y": {"num": 384,"den": 1}}, {"x": {"num": 330,"den": 1}, "y": {"num": 384,"den": 1}}],
[{"x": {"num": 240,"den": 1}, "y": {"num": 64,"den": 1}}, {"x": {"num": 272,"den": 1}, "y": {"num": 64,"den": 1}}, {"x": {"num": 272,"den": 1}, "y": {"num": 384,"den": 1}}, {"x": {"num": 240,"den": 1}, "y": {"num": 384,"den": 1}}],
[{"x": {"num": 314,"den": 1}, "y": {"num": 112,"den": 1}}, {"x": {"num": 442,"den": 1}, "y": {"num": 112,"den": 1}}, {"x": {"num": 442,"den": 1}, "y": {"num": 144,"den": 1}}, {"x": {"num": 314,"den": 1}, "y": {"num": 144,"den": 1}}],
[{"x": {"num": 64,"den": 1}, "y": {"num": 224,"den": 1}}, {"x": {"num": 538,"den": 1}, "y": {"num": 224,"den": 1}}, {"x": {"num": 538,"den": 1}, "y": {"num": 256,"den": 1}}, {"x": {"num": 64,"den": 1}, "y": {"num": 256,"den": 1}}],
[{"x": {"num": 160,"den": 1}, "y": {"num": 288,"den": 1}}, {"x": {"num": 304,"den": 1}, "y": {"num": 288,"den": 1}}, {"x": {"num": 304,"den": 1}, "y": {"num": 320,"den": 1}}, {"x": {"num": 160,"den": 1}, "y": {"num": 320,"den": 1}}],
[{"x": {"num": 160,"den": 1}, "y": {"num": 112,"den": 1}}, {"x": {"num": 304,"den": 1}, "y": {"num": 112,"den": 1}}, {"x": {"num": 304,"den": 1}, "y": {"num": 144,"den": 1}}, {"x": {"num": 160,"den": 1}, "y": {"num": 144,"den": 1}}]
]}